django_forbid/__init__.py
django_forbid/apps.py
django_forbid/middleware.py
django_forbid/skills/__init__.py
django_forbid/skills/forbid_device.py
django_forbid/skills/forbid_location.py
django_forbid/skills/forbid_network.py
django_forbid/templates/timezone.html
django_forbid-0.1.7.dist-info/licenses/LICENSE
django_forbid-0.1.7.dist-info/METADATA
django_forbid-0.1.7.dist-info/WHEEL
django_forbid-0.1.7.dist-info/top_level.txt
django_forbid-0.1.7.dist-info/RECORD
