Metadata-Version: 2.4
Name: django-forbid
Version: 0.1.7
Summary: Secure your Django app by controlling the access - grant or deny user access based on device and location, including VPN detection.
Author: Artyom Vancyan
Author-email: artyom@pysnippet.org
License: MIT
Project-URL: Documentation, https://docs.pysnippet.org/django-forbid/
Project-URL: Source Code, https://github.com/pysnippet/django-forbid/
Keywords: python,django,permit,forbid,access,device,secure,country,control,security,location,territory,vpn,detection,django-forbid
Platform: unix
Platform: linux
Platform: osx
Platform: win32
Classifier: Operating System :: OS Independent
Classifier: Development Status :: 5 - Production/Stable
Classifier: Framework :: Django
Classifier: Framework :: Django :: 2.1
Classifier: Framework :: Django :: 2.2
Classifier: Framework :: Django :: 3.1
Classifier: Framework :: Django :: 3.2
Classifier: Framework :: Django :: 4.1
Classifier: Framework :: Django :: 4.2
Classifier: Framework :: Django :: 5.1
Classifier: Framework :: Django :: 5.2
Classifier: Programming Language :: Python
Classifier: Programming Language :: Python :: 3
Classifier: Programming Language :: Python :: 3.7
Classifier: Programming Language :: Python :: 3.8
Classifier: Programming Language :: Python :: 3.9
Classifier: Programming Language :: Python :: 3.10
Classifier: Programming Language :: Python :: 3.11
Classifier: Programming Language :: Python :: 3.12
Classifier: License :: OSI Approved :: MIT License
Requires-Python: >=3.7
License-File: LICENSE
Requires-Dist: Django>=2.1
Requires-Dist: geoip2
Requires-Dist: device_detector
Dynamic: license-file
